openparams/__init__.py
openparams-0.0.1.dist-info/licenses/LICENSE
openparams-0.0.1.dist-info/METADATA
openparams-0.0.1.dist-info/WHEEL
openparams-0.0.1.dist-info/top_level.txt
openparams-0.0.1.dist-info/RECORD
