Metadata-Version: 2.4
Name: openparams
Version: 0.0.1
Summary: Coming soon — streaming model weights for research
Author: OpenWeights
License-Expression: MIT
Project-URL: Homepage, https://github.com/Aristide021/openweights
Project-URL: Repository, https://github.com/Aristide021/openweights
Classifier: Programming Language :: Python :: 3
Classifier: Development Status :: 3 - Alpha
Classifier: Intended Audience :: Science/Research
Classifier: Topic :: Scientific/Engineering :: Artificial Intelligence
Requires-Python: >=3.8
License-File: LICENSE
Dynamic: license-file
